robert_test_24/__init__.py
robert_test_24/_base_client.py
robert_test_24/_client.py
robert_test_24/_compat.py
robert_test_24/_constants.py
robert_test_24/_exceptions.py
robert_test_24/_files.py
robert_test_24/_models.py
robert_test_24/_qs.py
robert_test_24/_resource.py
robert_test_24/_response.py
robert_test_24/_streaming.py
robert_test_24/_types.py
robert_test_24/_version.py
robert_test_24/py.typed
robert_test_24/_utils/__init__.py
robert_test_24/_utils/_compat.py
robert_test_24/_utils/_datetime_parse.py
robert_test_24/_utils/_logs.py
robert_test_24/_utils/_proxy.py
robert_test_24/_utils/_reflection.py
robert_test_24/_utils/_resources_proxy.py
robert_test_24/_utils/_streams.py
robert_test_24/_utils/_sync.py
robert_test_24/_utils/_transform.py
robert_test_24/_utils/_typing.py
robert_test_24/_utils/_utils.py
robert_test_24/lib/.keep
robert_test_24/resources/__init__.py
robert_test_24/resources/beta/__init__.py
robert_test_24/resources/beta/batches.py
robert_test_24/resources/beta/beta.py
robert_test_24/resources/beta/cached_contents.py
robert_test_24/resources/beta/dynamic.py
robert_test_24/resources/beta/files.py
robert_test_24/resources/beta/generated_files.py
robert_test_24/resources/beta/corpora/__init__.py
robert_test_24/resources/beta/corpora/corpora.py
robert_test_24/resources/beta/corpora/permissions.py
robert_test_24/resources/beta/corpora/documents/__init__.py
robert_test_24/resources/beta/corpora/documents/chunks.py
robert_test_24/resources/beta/corpora/documents/documents.py
robert_test_24/resources/beta/models/__init__.py
robert_test_24/resources/beta/models/models.py
robert_test_24/resources/beta/models/operations.py
robert_test_24/resources/beta/rag_stores/__init__.py
robert_test_24/resources/beta/rag_stores/documents.py
robert_test_24/resources/beta/rag_stores/rag_stores.py
robert_test_24/resources/beta/rag_stores/upload.py
robert_test_24/resources/beta/tuned_models/__init__.py
robert_test_24/resources/beta/tuned_models/operations.py
robert_test_24-0.1.0.dist-info/METADATA
robert_test_24-0.1.0.dist-info/WHEEL
robert_test_24-0.1.0.dist-info/licenses/LICENSE
robert_test_24-0.1.0.dist-info/RECORD
